LICENSE
README.md
setup.py
jvQuant/__init__.py
jvQuant.egg-info/PKG-INFO
jvQuant.egg-info/SOURCES.txt
jvQuant.egg-info/dependency_links.txt
jvQuant.egg-info/requires.txt
jvQuant.egg-info/top_level.txt
jvQuant/ctp_client/__init__.py
jvQuant/sql_client/__init__.py
jvQuant/websocket_client/__init__.py
jvQuant/websocket_client/parse.py