Metadata-Version: 2.4
Name: jvQuant
Version: 1.20.2
Summary: Community Package Integrated Websocket quotations , CTP , and Database Client. 社区版量化工具包，集成WebSocket实时行情、CTP柜台以及在线数据库终端。支持量化交易平台所有功能，支持本地或云端使用。
Home-page: http://jvQuant.com
Author: jvQuant
Author-email: help@jvQuant.com
License: MIT License
Classifier: Programming Language :: Python :: 3
Classifier: License :: OSI Approved :: MIT License
Classifier: Operating System :: OS Independent
Requires-Python: >=3
License-File: LICENSE
Requires-Dist: websocket
Dynamic: author
Dynamic: author-email
Dynamic: classifier
Dynamic: description
Dynamic: description-content-type
Dynamic: home-page
Dynamic: license
Dynamic: license-file
Dynamic: requires-dist
Dynamic: requires-python
Dynamic: summary
